datagovuk/__init__.py
datagovuk/cache.py
datagovuk/session_wrapper.py
datagovuk/calls/__init__.py
datagovuk/calls/base.py
datagovuk/calls/datasets.py
datagovuk/calls/organisations.py
datagovuk/data_processors/__init__.py
datagovuk/data_processors/base.py
datagovuk/data_processors/csv.py
datagovuk/data_processors/geojson.py
datagovuk-0.1.3.dist-info/METADATA
datagovuk-0.1.3.dist-info/WHEEL
datagovuk-0.1.3.dist-info/entry_points.txt
datagovuk-0.1.3.dist-info/top_level.txt
datagovuk-0.1.3.dist-info/RECORD
